{"name":"ALC","slug":"ALC","count":1,"postlist":[{"title":"SAI-描述逻辑","uid":"fe7944109dd5437e82fba961634fce51","slug":"笔记/符号人工智能/描述逻辑","date":"2024-10-18T10:00:04.000Z","updated":"2025-11-15T13:30:59.862Z","comments":true,"path":"api/articles/笔记/符号人工智能/描述逻辑.json","keywords":null,"cover":"/img/post/笔记/符号人工智能/描述逻辑/cover.jpg","text":"是围绕对象的类别构建的知识的代表。...","permalink":"/post/笔记/符号人工智能/描述逻辑","photos":[],"count_time":{"symbolsCount":"2.8k","symbolsTime":"3 mins."},"categories":[{"name":"笔记-符号人工智能","slug":"笔记-符号人工智能","count":5,"path":"api/categories/笔记-符号人工智能.json"}],"tags":[{"name":"Symbolic Artificial Intelligence","slug":"Symbolic-Artificial-Intelligence","count":6,"path":"api/tags/Symbolic-Artificial-Intelligence.json"},{"name":"Description logics","slug":"Description-logics","count":1,"path":"api/tags/Description-logics.json"},{"name":"Attributive Concept Language with Complements","slug":"Attributive-Concept-Language-with-Complements","count":1,"path":"api/tags/Attributive-Concept-Language-with-Complements.json"},{"name":"ALC","slug":"ALC","count":1,"path":"api/tags/ALC.json"},{"name":"DL","slug":"DL","count":1,"path":"api/tags/DL.json"}],"author":{"name":"zExNocs","slug":"blog-author","avatar":"/img/avatar.jpg","link":"/","description":"<p>一个喜欢摸鱼的人。<br>去码头整点薯条。</p>","socials":{"github":"","twitter":"","stackoverflow":"","wechat":"","qq":"","weibo":"","zhihu":"","csdn":"","juejin":"","customs":{"github":{"icon":"/img/svg/github.svg","link":"https://github.com/zExNocs"},"bilibili":{"icon":"/img/svg/bilibili.svg","link":"https://space.bilibili.com/13423200"},"steam":{"icon":"/img/svg/steam.svg","link":"https://steamcommunity.com/id/zExNocs/"},"qq":{"icon":"/img/svg/QQ.svg","link":"https://qm.qq.com/cgi-bin/qm/qr?k=_glZz5Xy8An6DaliL38ZBfl7QhJGB_z9"}}}},"feature":false}]}